cisc108/__init__.py
cisc108/assertions.py
CISC108-0.4.dist-info/LICENSE
CISC108-0.4.dist-info/METADATA
CISC108-0.4.dist-info/WHEEL
CISC108-0.4.dist-info/top_level.txt
CISC108-0.4.dist-info/RECORD
