Metadata-Version: 2.1
Name: CISC108
Version: 0.4
Summary: Tools to help students write code.
Home-page: https://github.com/UD-CIS-Teaching/cisc108-python-support-library
Author: acbart
Author-email: acbart@udel.edu
License: MIT
Platform: UNKNOWN
Classifier: Programming Language :: Python :: 3
